integra_python_connector/__init__.py
integra_python_connector/__main__.py
integra_python_connector/src/adapters/__init__.py
integra_python_connector/src/adapters/ConnectorAdapter.py
integra_python_connector/src/adapters/ProcessorAdapter.py
integra_python_connector/src/api_router.py
integra_python_connector/src/builder.py
integra_python_connector/src/common/__init__.py
integra_python_connector/src/common/dependency_manager.py
integra_python_connector/src/common/enums.py
integra_python_connector/src/common/settings.py
integra_python_connector/src/dto/__init__.py
integra_python_connector/src/dto/responces/external_service.py
integra_python_connector/src/dto/skeletons/connector.py
integra_python_connector/src/dto/skeletons/processor.py
integra_python_connector/src/dto/views/connector_view.py
integra_python_connector/src/dto/views/processor_view.py
integra_python_connector/src/entity/parametr.py
integra_python_connector/src/external/simple_adapter.py
integra_python_connector/src/routers/__init__.py
integra_python_connector/src/routers/v1/__init__.py
integra_python_connector/src/routers/v1/base.py
integra_python_connector/src/routers/v1/configuration.py
integra_python_connector/src/routers/v1/processor.py
integra_python_connector/src/services/__init__.py
integra_python_connector/src/services/connector.py
integra_python_connector/src/services/external_service.py
integra_python_connector/src/services/processor.py
integra_python_connector-0.1.0.dist-info/METADATA
integra_python_connector-0.1.0.dist-info/WHEEL
integra_python_connector-0.1.0.dist-info/RECORD
